LICENSE
README.md
setup.py
heva_evse/__init__.py
heva_evse/base.py
heva_evse.egg-info/PKG-INFO
heva_evse.egg-info/SOURCES.txt
heva_evse.egg-info/dependency_links.txt
heva_evse.egg-info/requires.txt
heva_evse.egg-info/top_level.txt