Metadata-Version: 2.1
Name: heva-evse
Version: 0.0.2
Summary: Base for EVSE API wrappers.
Home-page: https://heva.energy
Author: HEVA
Author-email: conor@heva.energy
License: MIT
Platform: UNKNOWN
Classifier: License :: OSI Approved :: MIT License
Classifier: Programming Language :: Python :: 3.7
Requires-Python: >=3.7
License-File: LICENSE
